[
  { "name": "ดุสิต", "score": 100 },
  { "name": "ทุ่งครุ", "score": 92.45283018867924 },
  { "name": "บางขุนเทียน", "score": 91.61244944610515 },
  { "name": "บางมด", "score": 97.9797 },
  { "name": "บางรัก", "score": 100 },
  { "name": "ปทุมวัน", "score": 90.33420936191851 },
  { "name": "พญาไท", "score": 96.62921348314607 },
  { "name": "พระนคร", "score": 100 },
  { "name": "ภาษีเจริญ", "score": 76.49122807017544 },
  { "name": "ราชเทวี", "score": 97.83549783549783 },
  { "name": "ราษฎร์บูรณะ", "score": 97.85185185185185 }
]
